{"distinguished":null,"retrieved_on":1473807868,"gilded":0,"edited":false,"parent_id":"t3_tqol","id":"ctso7","author":"[deleted]","author_flair_text":null,"score":2,"ups":2,"author_flair_css_class":null,"created_utc":1165382544,"subreddit":"reddit.com","subreddit_id":"t5_6","link_id":"t3_tqol","stickied":false,"controversiality":0,"body":"In an attempt to prevent future use of these weapons of mass flatulation, TSA is drafting guidelines for what passengers can consume in the hours leading up to a flight.  Meanwhile, the White House is scrambling to prepare a speech declaring a War on Farting.","timestamp_epoch":1566236761,"message_id":"10825-6a79e0ea-16b5-43a4-86b3-3ac385058f17-1566236761"}