{"controversiality":1,"body":"Yeah me too - I can't see it. anyone know of an alternative link?","stickied":false,"link_id":"t3_txkn","subreddit_id":"t5_6","subreddit":"reddit.com","created_utc":1165492584,"author_flair_css_class":null,"ups":-1,"score":-1,"author":"Perenelle","author_flair_text":null,"id":"ctyuk","parent_id":"t1_ctyrq","edited":false,"gilded":0,"retrieved_on":1473807983,"distinguished":null,"timestamp_epoch":1566236762,"message_id":"13589-3c1086f0-d262-43a3-a6b4-eae4362c8a65-1566236762"}