{"subreddit":"reddit.com","score":-2,"ups":-2,"created_utc":1165542413,"author_flair_css_class":null,"controversiality":0,"body":"Excerpt:\r\n\r\n\"The courtroom, however, was empty on Wednesday, and for a simple reason: The court was out of cases. The question is, where have all the cases gone?\"","subreddit_id":"t5_6","stickied":false,"link_id":"t3_u28a","gilded":0,"distinguished":null,"retrieved_on":1473808045,"author":"mjk1093","author_flair_text":null,"edited":false,"id":"cu28b","parent_id":"t3_u28a","timestamp_epoch":1566236762,"message_id":"15069-3b9b591e-d57f-44a4-a856-64512f8d6265-1566236762"}