{"subreddit":"reddit.com","score":0,"ups":0,"created_utc":1165550321,"author_flair_css_class":null,"body":"If this isn't a country/government/judicial system in shambles, then I don't know what is.\r\n\r\n/where's the reset button","controversiality":1,"subreddit_id":"t5_6","stickied":false,"link_id":"t3_u28a","gilded":0,"distinguished":null,"retrieved_on":1473808052,"author_flair_text":null,"author":"artman","parent_id":"t3_u28a","id":"cu2lq","edited":false,"timestamp_epoch":1566236762,"message_id":"15305-8150e03d-dc3c-42f1-a456-4c6177add309-1566236762"}