{"created_utc":1165592727,"author_flair_css_class":null,"ups":1,"score":1,"subreddit":"reddit.com","stickied":false,"link_id":"t3_u2uh","subreddit_id":"t5_6","body":"I might get modded down for this, but here goes.  I think the guy was pretty naive to think that a telecom company like Verizon would sell their bandwidth at a just .002 cents per kb. Sure the management and call center people are stupid, but you should expect that from the beginning.  This is where the Internet would have been a more reliable source of information on their rates.  Less chance of human error.","controversiality":1,"retrieved_on":1473808087,"distinguished":null,"gilded":0,"parent_id":"t3_u2uh","edited":false,"id":"cu4ii","author_flair_text":null,"author":"ccamp","timestamp_epoch":1566236763,"message_id":"16144-927ca460-8ed4-42f3-b947-bc42c19b1bf2-1566236763"}