{"author":"Raoulmeister","author_flair_text":null,"id":"cu4sx","edited":false,"parent_id":"t3_u4l6","gilded":0,"distinguished":null,"retrieved_on":1473808092,"controversiality":0,"body":"In theory this guy is right. However in practice I think happiness is having something to *look* *forward* *to*.\r\n","subreddit_id":"t5_6","link_id":"t3_u4l6","stickied":false,"subreddit":"reddit.com","score":3,"ups":3,"author_flair_css_class":null,"created_utc":1165595740,"timestamp_epoch":1566236763,"message_id":"16271-3ea702f5-ee53-45f5-a3ed-37666a3ef9a1-1566236763"}