{"distinguished":null,"retrieved_on":1473807504,"gilded":0,"edited":false,"parent_id":"t3_t8ou","id":"ct9az","author":"[deleted]","author_flair_text":null,"score":5,"ups":5,"author_flair_css_class":null,"created_utc":1164997229,"subreddit":"reddit.com","subreddit_id":"t5_6","link_id":"t3_t8ou","stickied":false,"controversiality":0,"body":"Is there no \"vehicular homocide\" charge in Illinois?  How in the world could she not be charged with anything more significant?","timestamp_epoch":1566236758,"message_id":"1721-0c5d7eec-334b-4b78-b76d-581826e52bc6-1566236758"}