{"distinguished":null,"retrieved_on":1473808127,"gilded":0,"id":"cu6jt","edited":false,"parent_id":"t1_cu666","author_flair_text":null,"author":"marcusk","score":1,"ups":1,"author_flair_css_class":null,"created_utc":1165620785,"subreddit":"reddit.com","subreddit_id":"t5_6","link_id":"t3_u3al","stickied":false,"body":"don't think so, nasa have been going steadily downhill since the first moon landing and since there would be very little purpose to sending a probe that lands on mercury in the next 50 years (i.e. no one is gonna go to mercury to look for life) i'm pretty sure that it'll never happen...\r\n\r\nit's debatable whether nasa will even exist in the next 30 years...  the closest you'll get for seeing that kind of thing will be to go there as a tourist with a private firm ...","controversiality":0,"timestamp_epoch":1566236763,"message_id":"17314-b7fa8f45-cfe8-4cc0-a8ba-21d82ec9cb02-1566236763"}