{"link_id":"t3_t9m4","stickied":false,"subreddit_id":"t5_6","controversiality":0,"body":"Hosting Coupons is the website for big savings when choosing your next host. Here is where you can get webhosting coupons from great webhosts to save you money. You will also find news and reviews of several popular web hosting companies so as to fit your exact needs. Whichever host you choose, you're going to save some money by signing up. So, find a host, find a coupon and start saving big today.","author_flair_css_class":null,"created_utc":1165001301,"score":1,"ups":1,"subreddit":"reddit.com","id":"ct9m6","parent_id":"t3_t9m4","edited":false,"author_flair_text":null,"author":"hadrick","retrieved_on":1473807510,"distinguished":null,"gilded":0,"timestamp_epoch":1566236758,"message_id":"1889-3d5559a6-5932-4fa7-9fb5-c4af8c263416-1566236758"}