{"edited":false,"id":"cu9h4","parent_id":"t1_cu8mz","author_flair_text":null,"author":"rglovejoy","retrieved_on":1473808183,"distinguished":null,"gilded":0,"link_id":"t3_u8he","stickied":false,"subreddit_id":"t5_6","body":"Yeah, it isn't as though the \"Naughty Nurses\" are giving their customers sponge baths.","controversiality":1,"author_flair_css_class":null,"created_utc":1165695294,"score":0,"ups":0,"subreddit":"reddit.com","timestamp_epoch":1566236764,"message_id":"18931-767b2d20-e08b-49f4-9fb4-ba05782e751f-1566236764"}