{"distinguished":null,"retrieved_on":1473808214,"gilded":0,"id":"cub5r","parent_id":"t1_cub0a","edited":false,"author_flair_text":null,"author":"trutru","ups":7,"score":7,"created_utc":1165739600,"author_flair_css_class":null,"subreddit":"programming","subreddit_id":"t5_2fwo","stickied":false,"link_id":"t3_ualu","body":"Joel is making a specific point about programming language and attitude. You're just calling him a hater. Could you care to elaborate why he's so wrong that you don't even feel the need to explain why ?\r\n","controversiality":0,"timestamp_epoch":1566236764,"message_id":"19871-5992e17d-d501-43f8-b03a-dbc41777da0a-1566236764"}