{"controversiality":0,"body":"Then I would ask all atheists on here to please keep that in mind the next time you post about some Christian saying something you disagree with!","subreddit_id":"t5_6","stickied":false,"link_id":"t3_u9s2","subreddit":"reddit.com","score":-5,"ups":-5,"created_utc":1165785235,"author_flair_css_class":null,"author_flair_text":null,"author":"CarlH","edited":false,"parent_id":"t1_cubv9","id":"cucv8","gilded":0,"distinguished":null,"retrieved_on":1473808245,"timestamp_epoch":1566236765,"message_id":"20751-8c3d2ff9-0cff-4028-b874-a4d67c5e4f3f-1566236765"}