{"created_utc":1165820549,"author_flair_css_class":null,"score":1,"ups":1,"subreddit":"reddit.com","stickied":false,"link_id":"t3_tq6l","subreddit_id":"t5_6","body":"tautology removed??? are you serious? can you just refer to a [dictionary](http://www.answers.com/topic/atheism) the next time you need to pull this kind of thing? a vegetarian who will eat meat is not a vegetarian, and you mentioning a single vegetarian who doesn't have a problem with eating meat doesn't actually mean that vegetarians can eat meat and simultaneously embody and defy the very definition of the word. And **A** is definitely not true, for the same reasons that B and C *are* true, so any conclusions based thereafter are groundless. Please, you may have taken notes in philosophy class, but you certainly didn't allow for it to sink in. there are so many holes in your argument, it's swiss cheese. It makes me mad just to argue with you, this is like any other argument on the internet. when it's over, i'm still arguing with somebody over the internet.","controversiality":0,"retrieved_on":1473808277,"distinguished":null,"gilded":0,"id":"cuej0","parent_id":"t1_cudn9","edited":false,"author":"carpeliam","author_flair_text":null,"timestamp_epoch":1566236766,"message_id":"21735-1afc35af-ceb3-4936-9fc9-4d4ad22765bb-1566236766"}