{"score":1,"ups":1,"author_flair_css_class":null,"created_utc":1165913015,"subreddit":"reddit.com","subreddit_id":"t5_6","link_id":"t3_uj0x","stickied":false,"body":"Who cares?  People submit all kinds of things on reddit that don't get to the front page.  If the link \"fits\" with the reddit community, they'll mod it up, otherwise they won't.","controversiality":0,"distinguished":null,"retrieved_on":1473808373,"gilded":0,"edited":false,"id":"cujlp","parent_id":"t1_cuj8c","author_flair_text":null,"author":"furyg3","timestamp_epoch":1566236767,"message_id":"24370-28b1443d-f7de-46e7-82dd-ec7d57374026-1566236767"}