{"subreddit_id":"t5_2fwo","stickied":false,"link_id":"t3_ujgi","body":"\"This is how I think it works\"\r\n\r\nWell, I think it works differently, so there!","controversiality":0,"score":6,"ups":6,"created_utc":1165936898,"author_flair_css_class":null,"subreddit":"programming","parent_id":"t3_ujgi","edited":false,"id":"cuksh","author_flair_text":null,"author":"sabernar","distinguished":null,"retrieved_on":1473808396,"gilded":0,"timestamp_epoch":1566236767,"message_id":"24870-e2b7bab9-4a19-42cd-9f9f-c996586eaed3-1566236767"}