{"subreddit_id":"t5_6","link_id":"t3_uksn","stickied":false,"controversiality":0,"body":"########    ###                    \r\n                                              #     ######   ##                  \r\n                                             #         #      ##                 \r\n                                            ##        ##      ##                \r\n                      #####                ##          ##    ##                \r\n                     ##    #################             ####                 \r\n                    #    ###                #####                          \r\n                   ##  ###                      ###                             \r\n                    ####                          ###                          \r\n                     ##         ###                 ########                  \r\n                    ##         ######                  ##  ##                \r\n                    ##         #####        ####        ##   #               \r\n                    ##          ###         #####        #   #                \r\n                     #                      #####        #  ##                \r\n                     ##                      ###         ###                \r\n                      ##                                  #                     \r\n                       ##      ##                        ##                    \r\n                        ##      ###       ##            ##                    \r\n                          ##      #########           ##                     \r\n                            ####                   ###                        \r\n                            ##  #######         ####                           \r\n                          ####        ############                            \r\n                         ## ##                 ## #                            \r\n                        ##  ##                 ## ##                          \r\n                        ##  ##                 #   # \r\n                        ##  ##                 #   #                      \r\n                        ##  ##                 #   #                            \r\n                         #   #                 #  ##                           \r\n                         ##  #                 #  ##                            \r\n                          ## ##               ## ##                            \r\n                           ####               ####                             \r\n                              #              ##                                \r\n                               #            ##                                  \r\n                          ########          #######                             \r\n                         ##      ##        ##     ##                           \r\n                         ##       ###    ###       ##                    \r\n                          ##########################                \r\n\r\nEdit: Ok, I admit I'm not too good at doing ascii art","score":3,"ups":3,"author_flair_css_class":null,"created_utc":1165941485,"subreddit":"reddit.com","edited":false,"parent_id":"t3_uksn","id":"cul4u","author_flair_text":null,"author":"Dauntless","distinguished":null,"retrieved_on":1473808401,"gilded":0,"timestamp_epoch":1566236767,"message_id":"25052-15b10824-814d-4762-bb1b-5594bba5fede-1566236767"}