{"score":4,"ups":4,"created_utc":1166101930,"author_flair_css_class":null,"subreddit":"reddit.com","subreddit_id":"t5_6","stickied":false,"link_id":"t3_uoqx","body":"You would think with all the lead flying through the air in Iraq that there would be plenty!","controversiality":0,"distinguished":null,"retrieved_on":1473808517,"gilded":0,"parent_id":"t1_cuoyb","edited":false,"id":"curdh","author":"[deleted]","author_flair_text":null,"timestamp_epoch":1566236768,"message_id":"27894-95742af8-7de5-4ac2-9e67-9f6bd409db2d-1566236768"}