{"author":"[deleted]","author_flair_text":null,"edited":false,"id":"cutt1","parent_id":"t1_cutmt","gilded":0,"distinguished":null,"retrieved_on":1473808562,"controversiality":1,"body":"Teachers should be paid/promoted based on their effectiveness.\r\n\r\nI am not talking about teachers in the worst \"inner city\" schools, just regular ones.","subreddit_id":"t5_6","stickied":false,"link_id":"t3_ut1n","subreddit":"reddit.com","score":-4,"ups":-4,"created_utc":1166136858,"author_flair_css_class":null,"timestamp_epoch":1566236769,"message_id":"29126-eab72f65-8944-415c-81f3-a0392e15433a-1566236769"}