{"edited":false,"id":"cuul6","parent_id":"t3_ushl","author":"[deleted]","author_flair_text":null,"retrieved_on":1473808577,"distinguished":null,"gilded":0,"stickied":false,"link_id":"t3_ushl","subreddit_id":"t5_mouw","body":"Excellent, now make it tiny and run for a year on a watch battery!","controversiality":0,"created_utc":1166148760,"author_flair_css_class":null,"score":2,"ups":2,"subreddit":"science","timestamp_epoch":1566236769,"message_id":"29560-048f1d74-a933-4c83-a1fd-e3daacb1a277-1566236769"}