{"score":8,"ups":8,"author_flair_css_class":null,"created_utc":1166162846,"subreddit":"programming","subreddit_id":"t5_2fwo","link_id":"t3_utqb","stickied":false,"body":"I've yet to meet a high level, serious, programming language without these database drivers.\r\n\r\nIn fact, they usually have several varieties, depending on people's tastes.  Perhaps a low-level socket-version.  Or a direct interface to the C libraries.  Most likely, they have higher level interfaces built on top, ranging from as simple as just queries, to whole object-oriented&lt;-&gt;relational automated interfaces.\r\n\r\nGUI libraries?  You realize, Smalltalk programmers basically invented the GUI?  Don't get me started on the java crap that exists... calls itself an \"interface library.\"\r\n\r\n","controversiality":0,"distinguished":null,"retrieved_on":1473808589,"gilded":0,"edited":false,"id":"cuv8t","parent_id":"t1_cuurd","author":"ricercar","author_flair_text":null,"timestamp_epoch":1566236769,"message_id":"29860-564c5605-fe2d-4eb9-8e21-b2bc369f36f1-1566236769"}