{"author_flair_css_class":null,"created_utc":1166168420,"score":1,"ups":1,"subreddit":"reddit.com","link_id":"t3_uk6i","stickied":false,"subreddit_id":"t5_6","body":"u fucking idiot, it was most definitely staged. not my fault you're a retard.","controversiality":0,"retrieved_on":1473808593,"distinguished":null,"gilded":0,"parent_id":"t1_cumgt","edited":false,"id":"cuvh3","author_flair_text":null,"author":"poxy1","timestamp_epoch":1566236769,"message_id":"29947-638f9641-415d-4761-bcf5-2fb298fa530a-1566236769"}