{"subreddit":"programming","score":1,"ups":1,"author_flair_css_class":null,"created_utc":1166196888,"controversiality":0,"body":"To paraphrase someone else: \"Go do it.\"\r\n\r\nUntil we see this, we have reason to believe when things get down and dirty there may be good reasons why no commercially successful games have been written in, for example, Lisp. (And yes I know about Jak &amp; Daxter, and no it doesn't count as only the animation system was written in a custom version of Lisp which allowed embedded assembly, and the whole system was later thrown out!)\r\n\r\nI'm not saying you're wrong, I'm saying \"It *would be* so much better\" doesn't carry much weight.\r\n\r\n(And for the record, few commercially succesful games are written using OpenGL, for better or worse D3D rules that niche, but keep on hackin')\r\n\r\nEdit: changed 'almost no' to 'few', after the counter-example (the exception proves the rule) provided below.","subreddit_id":"t5_2fwo","link_id":"t3_uuzg","stickied":false,"gilded":0,"distinguished":null,"retrieved_on":1473808623,"author":"jbstjohn","author_flair_text":null,"edited":false,"parent_id":"t1_cuvbw","id":"cux17","timestamp_epoch":1566236769,"message_id":"30583-3ac568d3-1039-46aa-bd8c-3cc21a5cebc8-1566236769"}