{"link_id":"t3_uyrw","stickied":false,"subreddit_id":"t5_6","body":"It's hard to define what a firewall is.\r\n\r\nOn Linux NAT routing and network restrictions are done by iptables, so only a part of iptables is the firewall? Those Windows firewalls parse your email for viruses. Is that a firewalls job?","controversiality":0,"author_flair_css_class":null,"created_utc":1166265046,"score":5,"ups":5,"subreddit":"reddit.com","parent_id":"t1_cuzkl","id":"cv0gi","edited":false,"author":"beza1e1","author_flair_text":null,"retrieved_on":1473808688,"distinguished":null,"gilded":0,"timestamp_epoch":1566236770,"message_id":"32263-571c6315-1ecd-4c6c-bc71-cc3abe3ee9e1-1566236770"}