{"subreddit_id":"t5_6","stickied":false,"link_id":"t3_v1dj","controversiality":0,"body":"These people are getting nothing for a sentence when you consider how much money they are making.  Their sentences are only encouraging others to take the chance.","score":1,"ups":1,"created_utc":1166290587,"author_flair_css_class":null,"subreddit":"reddit.com","id":"cv1dq","edited":false,"parent_id":"t3_v1dj","author":"eddy222","author_flair_text":null,"distinguished":null,"retrieved_on":1473808706,"gilded":0,"timestamp_epoch":1566236770,"message_id":"32545-d1a22d62-7230-44fd-82d6-ca9688c11df8-1566236770"}