{"retrieved_on":1473808709,"distinguished":null,"gilded":0,"edited":false,"parent_id":"t3_v1do","id":"cv1k5","author_flair_text":null,"author":"muttleee","author_flair_css_class":null,"created_utc":1166294715,"score":1,"ups":1,"subreddit":"reddit.com","link_id":"t3_v1do","stickied":false,"subreddit_id":"t5_6","body":"This article seems to criticise poor journalism rather than poor science.","controversiality":0,"timestamp_epoch":1566236770,"message_id":"32614-8bfdcbeb-1c13-4a5d-bbec-dde78beecc63-1566236770"}