{"gilded":0,"retrieved_on":1473808751,"distinguished":null,"author_flair_text":null,"author":"fredrikj","id":"cv3q0","edited":false,"parent_id":"t3_v2wa","subreddit":"reddit.com","created_utc":1166356752,"author_flair_css_class":null,"score":35,"ups":35,"body":"Reddit should automatically prefix submission titles with \"Awesome\".","controversiality":0,"stickied":false,"link_id":"t3_v2wa","subreddit_id":"t5_6","timestamp_epoch":1566236771,"message_id":"33737-48c0a657-0d1c-4a22-b201-967d732a76ea-1566236771"}