{"edited":false,"id":"cv4hu","parent_id":"t1_cv43q","author_flair_text":null,"author":"igeldard","distinguished":null,"retrieved_on":1473808765,"gilded":0,"subreddit_id":"t5_6","link_id":"t3_v3qq","stickied":false,"body":"Very true Taladar, and Christian fundamentalists did use to do just that - consider the mania over 'witchcraft' which led to the torture and murder of hundreds of thousands of women by religious bigots. No doubt there are those Christians in the US and elsewhere who would gladly restore the Inquisition et al.","controversiality":0,"ups":5,"score":5,"author_flair_css_class":null,"created_utc":1166377248,"subreddit":"reddit.com","timestamp_epoch":1566236771,"message_id":"34112-15eeb9b1-6cc1-4eb3-8649-ee888f246ca0-1566236771"}