{"score":-4,"ups":-4,"author_flair_css_class":null,"created_utc":1166448507,"subreddit":"reddit.com","subreddit_id":"t5_6","link_id":"t3_v6h2","stickied":false,"controversiality":0,"body":"Well, if I'd substituted swaddlers and practitioners of hardening, those wouldn't have meant anything to you. Hint: infant torture.","distinguished":null,"retrieved_on":1473808821,"gilded":0,"edited":false,"parent_id":"t1_cv7hc","id":"cv7ia","author":"richardkulisz","author_flair_text":null,"timestamp_epoch":1566236771,"message_id":"35690-5a34781c-5980-41c3-afc1-766209e5e781-1566236771"}