{"edited":false,"id":"cv7jj","parent_id":"t3_v6rx","author":"cot6mur3","author_flair_text":null,"retrieved_on":1473808822,"distinguished":null,"gilded":0,"link_id":"t3_v6rx","stickied":false,"subreddit_id":"t5_2fwo","body":"Great article.  I'm glad to see, for a change, some _positive_ commentary on C++, as C++ _is_ (IMHO) an essential and very high quality language for many programming tasks, even today (late 2006).  Also, C++0x (09 is looking likely, I've read), unlike improvements to many other programming languages that have been embraced by languages' designers this decade, is looking all-around sensible - no serious mistakes that I can see.  :)  I am pleasantly surprised by this.\r\n\r\nI'm looking forward to his follow-up on D.","controversiality":0,"author_flair_css_class":null,"created_utc":1166449447,"score":5,"ups":5,"subreddit":"programming","timestamp_epoch":1566236771,"message_id":"35716-4be4580f-5bb5-45cd-827d-8b3ff8be3e76-1566236771"}