{"link_id":"t3_v91g","stickied":false,"subreddit_id":"t5_6","body":"All new age art sucks.\r\n\r\nAll new music sucks.\r\n\r\nAll new movies suck, as do all new television programs.\r\n\r\nNow you kids beat it!  Get off my lawn!","controversiality":0,"author_flair_css_class":null,"created_utc":1166481611,"score":1,"ups":1,"subreddit":"reddit.com","edited":false,"id":"cva3s","parent_id":"t3_v91g","author":"indigoshift","author_flair_text":null,"retrieved_on":1473808871,"distinguished":null,"gilded":0,"timestamp_epoch":1566236772,"message_id":"36987-32bbee80-5cda-46c1-961e-d744e91d9542-1566236772"}