{"link_id":"t3_vm4x","stickied":false,"subreddit_id":"t5_6","body":"Improve your sales with the power of sales forecasting and reporting by Foresitespa. Sales pipeline management has never been easier.","controversiality":0,"author_flair_css_class":null,"created_utc":1166702062,"score":1,"ups":1,"subreddit":"reddit.com","id":"cvm52","parent_id":"t3_vm4x","edited":false,"author_flair_text":null,"author":"willowsong","retrieved_on":1473809103,"distinguished":null,"gilded":0,"timestamp_epoch":1566236774,"message_id":"43017-3d3e8eb8-977a-48ad-b8e9-56e6b9b37eaa-1566236774"}