{"retrieved_on":1473809103,"distinguished":null,"gilded":0,"id":"cvm6w","edited":false,"parent_id":"t1_cvm0g","author_flair_text":null,"author":"[deleted]","created_utc":1166703374,"author_flair_css_class":null,"score":8,"ups":8,"subreddit":"reddit.com","stickied":false,"link_id":"t3_vk0o","subreddit_id":"t5_6","body":"There are about 100 times as many people insisting on the opposite. I greatly prefer the white-on-black (actually light gray on dark gray is a lot more readable), much better for eye strain if you're looking at a monitor for more than a few minutes. Might be slightly harder to read, but it beats the sensation of staring into headlights for hours at a time. What's really dumb is that people even have to argue about this... you'd think by now there'd be a way for people to choose background/foreground text colors on the websites they're viewing that's easier than manually creating a separate CSS file for every site. In the meantime Firefox [Stylish](https://addons.mozilla.org/firefox/2108/) extension is pretty good for popular sites, or most sites if you're willing to do a small bit of CSS editing.","controversiality":0,"timestamp_epoch":1566236774,"message_id":"43035-655793d2-a13e-4e24-8ac2-f98399d16385-1566236774"}