{"gilded":0,"distinguished":null,"retrieved_on":1473809114,"author_flair_text":null,"author":"orick","edited":false,"parent_id":"t3_vlsg","id":"cvmr6","subreddit":"reddit.com","ups":-17,"score":-17,"created_utc":1166714254,"author_flair_css_class":null,"controversiality":0,"body":"oral, hmm... shouldn't that mean there won't be enough actual evidence to convict him???\r\n","subreddit_id":"t5_6","stickied":false,"link_id":"t3_vlsg","timestamp_epoch":1566236774,"message_id":"43245-9b0e1da0-0d8f-42e3-aff5-7ec6082ea5d7-1566236774"}