{"edited":false,"parent_id":"t3_vsbh","id":"cvske","author_flair_text":null,"author":"degustiapollo11","distinguished":null,"retrieved_on":1473809226,"gilded":0,"subreddit_id":"t5_6","link_id":"t3_vsbh","stickied":false,"body":"Mutated alien virus escapes lab: causes death by neverending orgasms.","controversiality":0,"score":3,"ups":3,"author_flair_css_class":null,"created_utc":1166826387,"subreddit":"reddit.com","timestamp_epoch":1566236775,"message_id":"46328-412e98e9-3f6c-4414-bbe9-442005ca1c2a-1566236775"}