{"gilded":0,"retrieved_on":1473809243,"distinguished":null,"author":"Notclevr","author_flair_text":null,"edited":false,"id":"cvtfm","parent_id":"t1_cvr4t","subreddit":"reddit.com","author_flair_css_class":null,"created_utc":1166848771,"score":-2,"ups":-2,"controversiality":0,"body":"Why worse??  Concrete is pretty hard.\r\n\r\nAnd I think the answer for water is the same as concrete--try to do the five point roll to spread out the damage.  They don't mention to protect your head and try not to let your neck snap on impact.\r\n\r\nI was also surprised the \"go limp\" strategy wasn't discussed.","link_id":"t3_vqno","stickied":false,"subreddit_id":"t5_6","timestamp_epoch":1566236775,"message_id":"46824-600b3727-98e8-4a6f-80ba-8809a8d4b56c-1566236775"}