{"author":"scorpan","author_flair_text":null,"id":"cvtp6","edited":false,"parent_id":"t3_vshb","gilded":0,"distinguished":null,"retrieved_on":1473809248,"body":"Conclusion:  Taking pictures of squirrels in your backyard is NSFW.","controversiality":0,"subreddit_id":"t5_6","link_id":"t3_vshb","stickied":false,"subreddit":"reddit.com","ups":42,"score":42,"author_flair_css_class":null,"created_utc":1166857528,"timestamp_epoch":1566236775,"message_id":"46965-424e8059-29f4-4fe1-8e1e-debab60296b1-1566236775"}