{"gilded":0,"distinguished":null,"retrieved_on":1473809275,"author_flair_text":null,"author":"losvedir","id":"cvv5u","parent_id":"t3_vtyf","edited":false,"subreddit":"reddit.com","ups":0,"score":0,"created_utc":1166902185,"author_flair_css_class":null,"controversiality":0,"body":"Seriously, I'm so impressed with all the guys on youtube that are a part of Candyrat recrods. Check out all the guys posted by rpoland on there - Andy McKee, Bob Ross, Antoine Dufour, etc. \r\n\r\n*This* is what a record company should be these days. They find great talent and give them a chance to record. If you go to the website you can download all the songs for free, or buy them for better quality. I got an Andy McKee CD just a week ago to support them, and because he's awesome.","subreddit_id":"t5_6","stickied":false,"link_id":"t3_vtyf","timestamp_epoch":1566236775,"message_id":"47639-ab9e3322-e169-43fc-ad53-c5ed8f97cd7c-1566236775"}