{"gilded":0,"retrieved_on":1473809285,"distinguished":null,"author_flair_text":null,"author":"Reg_Spyder","edited":false,"id":"cvvod","parent_id":"t1_cvvfg","subreddit":"reddit.com","created_utc":1166916051,"author_flair_css_class":null,"ups":3,"score":3,"body":"CD sales are profitable for the industry, rarely for the artists. we need to seperate the artists from the legions of overpaid execs and their coke and hookers, their kickbacks at over-priced recording studios, their 1st class treatment of artists at top hotels and business class flights that all end up on the recoupment part of the bill - usually meaning that artists get paid shite all for their efforts, even when the record companies coin in millions.\r\n\r\nartists selling straight through to their fanbase could make a living selling for far less, or selling in much smaller numbers. Fat record execs will starve and die. There will be cheering in the streets, but a lot of disappointed coke dealers.","controversiality":0,"stickied":false,"link_id":"t3_vtf3","subreddit_id":"t5_6","timestamp_epoch":1566236775,"message_id":"47876-8a218a92-1f74-49e8-b259-3f35feefd3ad-1566236775"}