{"gilded":0,"retrieved_on":1473809306,"distinguished":null,"author_flair_text":null,"author":"NitsujTPU","edited":false,"parent_id":"t3_vw33","id":"cvwpg","subreddit":"reddit.com","created_utc":1166956999,"author_flair_css_class":null,"score":2,"ups":2,"body":"Why do you care?\r\n\r\n\r\n*Look at us, we're atheists.  Despite this, we spend all day thinking about religion.*\r\n\r\n\r\nSheesh.\r\n\r\n\r\nThe other one is:\r\n\r\n\r\n*Atheism is the product of sane, rational, scientific thought.*\r\n\r\n\r\nWell, if you're a scientist, what science do you study?  I'll give you an example.  A physicist studies physics.  A chemist studies chemistry.  An atheist studies theology... but theology isn't science.  Get it?","controversiality":1,"stickied":false,"link_id":"t3_vw33","subreddit_id":"t5_6","timestamp_epoch":1566236777,"message_id":"48383-2407b537-c3e7-490d-8fd1-14606c6af2e4-1566236777"}