{"ups":11,"score":11,"created_utc":1167147348,"author_flair_css_class":null,"subreddit":"reddit.com","subreddit_id":"t5_6","stickied":false,"link_id":"t3_w23j","controversiality":0,"body":"netbuzz, hm. I laughed all the way through it.\r\n\r\n&gt; Metafilter: Unhelpful link text. Extra links added for padding that have little to do with the main topic of the entry. Are extremely loaded rhetorical questions the only thing that can save us now?\r\n\r\nThat is true, every time someone recommends Metafilter and I check it out, parsing it is very tedious.","distinguished":null,"retrieved_on":1473809411,"gilded":0,"edited":false,"parent_id":"t3_w23j","id":"cw2a7","author_flair_text":null,"author":"[deleted]","timestamp_epoch":1566236778,"message_id":"51222-4d514438-d7f2-4591-a85a-e6a638fc6f3c-1566236778"}