{"ups":2,"score":2,"created_utc":1167229015,"author_flair_css_class":null,"subreddit":"reddit.com","subreddit_id":"t5_6","stickied":false,"link_id":"t3_w37e","body":"Twilight Princess, is not graphically all that great. Still, I have to agree on the loading times; it's never going to get even close to XBox 360 loading times, for example, because it lacks the RAM to hold that much data anyway!\r\n","controversiality":0,"distinguished":null,"retrieved_on":1473809467,"gilded":0,"edited":false,"id":"cw5b0","parent_id":"t1_cw3qx","author_flair_text":null,"author":"rnicoll","timestamp_epoch":1566236778,"message_id":"52878-7b1f307a-8727-4f14-9942-47ee197b9e9c-1566236778"}