{"subreddit":"reddit.com","created_utc":1167249134,"author_flair_css_class":null,"score":0,"ups":0,"body":"you are such an ass.\r\n\r\nYou should know better (or you actually do) being a Canadian, you know that a many of us in the US live more than 10  miles aways from where we work and/or to the nearest mass transit, but you couldn't help yourself huh?\r\n\r\nNot every place in America is NYC.\r\n\r\n\r\n\r\nHad to insult America today didn't you?\r\n\r\n\r\nHere ya go jackass.. you and you fellow Canucks are [fatasses](http://www.parl.gc.ca/information/library/PRBpubs/prb0511-e.htm) too, you just don't get the same press. (and that's an older study)\r\n\r\n\r\nCanada may not have as many as the US, but your probably one of them. Trolls usually are.","controversiality":1,"stickied":false,"link_id":"t3_w2xa","subreddit_id":"t5_6","gilded":0,"retrieved_on":1473809491,"distinguished":null,"author_flair_text":null,"author":"gormly","edited":false,"id":"cw6i4","parent_id":"t1_cw6gi","timestamp_epoch":1566236778,"message_id":"53566-3c7d29f9-a2c6-4f3c-8c13-ff375e912719-1566236778"}