{"id":"cw7ev","edited":false,"parent_id":"t1_cw77n","author_flair_text":null,"author":"[deleted]","retrieved_on":1473809509,"distinguished":null,"gilded":0,"stickied":false,"link_id":"t3_w6n9","subreddit_id":"t5_2fwo","body":"Unless the chapters you're talking about are unbelievably short, \"chapters\" and \"whole pages\" should probably be interchanged in there. Someone with a haskell.org login should fix that.","controversiality":0,"created_utc":1167268314,"author_flair_css_class":null,"score":1,"ups":1,"subreddit":"programming","timestamp_epoch":1566236779,"message_id":"54084-66355a64-7f8c-47d5-981a-67e6ce327ad6-1566236779"}