{"gilded":0,"retrieved_on":1473807656,"distinguished":null,"author_flair_text":null,"author":"bevets","id":"cthd2","edited":false,"parent_id":"t3_tgvw","subreddit":"reddit.com","created_utc":1165182723,"author_flair_css_class":null,"score":-36,"ups":-36,"body":"Atheist fights church effort to move museums evolutionism talismen.\r\n\r\nFixed it.","controversiality":0,"stickied":false,"link_id":"t3_tgvw","subreddit_id":"t5_6","timestamp_epoch":1566236759,"message_id":"5432-8979d4f3-b7ee-4352-8634-ccbe3ce46875-1566236759"}