{"score":1,"ups":1,"created_utc":1167313961,"author_flair_css_class":null,"subreddit":"reddit.com","subreddit_id":"t5_6","stickied":false,"link_id":"t3_w547","body":"And yet much of the medical community sees little ethical problem with distributing drugs, sometimes every bit as life-saving as an organ transplant, on the basis of ability to pony up cash.","controversiality":0,"distinguished":null,"retrieved_on":1473809537,"gilded":0,"id":"cw8xn","edited":false,"parent_id":"t1_cw7n0","author_flair_text":null,"author":"asciilifeform","timestamp_epoch":1566236779,"message_id":"54825-1451e94c-5d89-4def-96da-5692979166b2-1566236779"}