{"distinguished":null,"retrieved_on":1473809544,"gilded":0,"edited":false,"parent_id":"t1_cw98q","id":"cw9az","author":"bhagany","author_flair_text":null,"score":-9,"ups":-9,"author_flair_css_class":null,"created_utc":1167320526,"subreddit":"reddit.com","subreddit_id":"t5_6","link_id":"t3_w8u1","stickied":false,"controversiality":1,"body":"FTA:\r\n\r\n&gt; he said his comments could be published at any time after his death\r\n\r\nHe died before his statements were released _on purpose_.  This is also clearly stated in the reddit headline.\r\n\r\nFurthermore, I don't mind that he wanted his last years to be peaceful.  Nothing wrong with that.  But if that's the way you want it, then keep your mouth shut on things like this.\r\n\r\nOn the other hand, if you want your opinions to be made public, have the guts to put them out there while people can still argue with you.","timestamp_epoch":1566236779,"message_id":"54993-2f0fe1c5-9242-497b-a874-09cf26e86447-1566236779"}