{"body":"Last November, Evan from Michigan ate for only $1 per day and then wrote about it on his blog. He's now announced a new community driven experiment that is along the same vein, but this time around he's letting the Internet community at large tell him what to do. The coolest part is that he's willing to go anywhere in the world to do it.","controversiality":0,"link_id":"t3_wao9","stickied":false,"subreddit_id":"t5_6","subreddit":"reddit.com","author_flair_css_class":null,"created_utc":1167343936,"ups":1,"score":1,"author":"elmuchoprez","author_flair_text":null,"edited":false,"parent_id":"t3_wao9","id":"cwaoa","gilded":0,"retrieved_on":1473809569,"distinguished":null,"timestamp_epoch":1566236779,"message_id":"55662-3623e227-8417-4c14-8be2-d86f5fc50d85-1566236779"}