{"score":4,"ups":4,"created_utc":1167354230,"author_flair_css_class":null,"subreddit":"reddit.com","subreddit_id":"t5_6","stickied":false,"link_id":"t3_w8sr","body":"Uhh...  non-subject?  Theology is the study of religion.  Even if god doesn't exist, religions still do.  So...  non-subject?    People still get the occasional degree in it, so far as I know, and knowing the topic you're talking about is generally helpful in any debate.","controversiality":0,"distinguished":null,"retrieved_on":1473809579,"gilded":0,"parent_id":"t1_cwar7","edited":false,"id":"cwb7j","author_flair_text":null,"author":"teamjimmyy","timestamp_epoch":1566236779,"message_id":"55969-abfc91c0-6b72-4042-8177-72d3fcdbf7b6-1566236779"}