{"author_flair_text":null,"author":"grauenwolf","edited":false,"id":"cwdr1","parent_id":"t1_cwdgx","gilded":0,"retrieved_on":1473809628,"distinguished":null,"body":"I'm sure they would if not for the fact that cars are expensive to ship. It is most cost effective to fly the blogger to the test track and give them a hotel room for the weekend.","controversiality":0,"stickied":false,"link_id":"t3_wa4q","subreddit_id":"t5_6","subreddit":"reddit.com","created_utc":1167418125,"author_flair_css_class":null,"score":1,"ups":1,"timestamp_epoch":1566236779,"message_id":"57197-f3b67919-f92b-476d-921e-a3c34f5735b6-1566236779"}