{"gilded":0,"retrieved_on":1473809633,"distinguished":null,"author":"einexile","author_flair_text":null,"id":"cwe33","parent_id":"t1_cwdc9","edited":false,"subreddit":"reddit.com","created_utc":1167423370,"author_flair_css_class":null,"score":7,"ups":7,"controversiality":0,"body":"Truth of the matter is some of us just read a few words and then click the mwheel. (We're opening every potentially interesting link at once.) Most of us then wince at our own foolishness and turn the speakers down as two or three different videos start playing at a time.\r\n\r\nApparently at least one person finds this all pretty upsetting. Maybe he should be more impressive at work so he feels comfortable asking his boss for speakers with a volume knob.","stickied":false,"link_id":"t3_wcg1","subreddit_id":"t5_6","timestamp_epoch":1566236779,"message_id":"57393-e7415d78-605b-4109-bb74-369a4961a73f-1566236779"}