{"gilded":0,"distinguished":null,"retrieved_on":1473809756,"author":"sketerpot","author_flair_text":null,"id":"cwkoa","edited":false,"parent_id":"t1_cwk6q","subreddit":"reddit.com","score":13,"ups":13,"author_flair_css_class":null,"created_utc":1167598628,"body":"From the article:\r\n\r\n&gt; If you have a copy of XP to use, guess what? The key that comes with the HP box is restricted to the version of Windows on the restore CD. Vanilla XP will not work, nor will any of the copies I have lying around. Your choice, use only HP hardware or buy a copy of XP. A big FU to MS and HP for this little ray of sunshine.","controversiality":0,"subreddit_id":"t5_6","link_id":"t3_wjvh","stickied":false,"timestamp_epoch":1566236780,"message_id":"60720-c12a4ce3-8727-4cfd-828e-66d1001ba4f8-1566236780"}