{"subreddit":"reddit.com","created_utc":1165269281,"author_flair_css_class":null,"ups":3,"score":3,"body":"That explanation makes no sense, either, isalpha. If the writer was confusing the month with the date, then he would have said \"November 9,\" rather than \"09 Sept.\" \r\n\r\nAnd besides, who hasn't heard it referred to as \"September 11\" on countless broadcasts? It's one of those dates people don't tend to screw up.","controversiality":0,"stickied":false,"link_id":"t3_tk02","subreddit_id":"t5_6","gilded":0,"retrieved_on":1473807744,"distinguished":null,"author":"jamie21310","author_flair_text":null,"id":"ctm17","edited":false,"parent_id":"t1_ctl6f","timestamp_epoch":1566236760,"message_id":"7602-83e750b8-d139-49a3-9fe9-9d1ad5cdb56d-1566236760"}