{"subreddit":"reddit.com","score":2,"ups":2,"created_utc":1165345205,"author_flair_css_class":null,"body":"I don't think there's anything irritating about it. Unless they criticized me and I wanted ammunition to use against them. Something to use to hate them back. ;)","controversiality":0,"subreddit_id":"t5_6","stickied":false,"link_id":"t3_tpok","gilded":0,"distinguished":null,"retrieved_on":1473807825,"author_flair_text":null,"author":"fnord123","edited":false,"id":"ctqe8","parent_id":"t1_ctqcg","timestamp_epoch":1566236761,"message_id":"9564-a29f8be2-e99f-418c-9db6-14ffe2da3cb1-1566236761"}